{
  "schemaVersion": "2.0.0",
  "generatedAt": "2026-06-04T07:59:10.425487Z",
  "generated_at": "2026-06-04T07:59:10.425491Z",
  "fetchedAt": 1780559950425,
  "sourceMode": "snapshot-worker-v2",
  "indices": [
    {
      "name": "NIFTY 50",
      "symbol": "^NSEI",
      "value": "23,367.35",
      "change": "-38.25",
      "changePercent": "-0.16",
      "direction": "down",
      "currency": "₹",
      "sourceMode": "yahoo-yfinance"
    },
    {
      "name": "SENSEX",
      "symbol": "^BSESN",
      "value": "74,218.49",
      "change": "-127.68",
      "changePercent": "-0.17",
      "direction": "down",
      "currency": "₹",
      "sourceMode": "yahoo-yfinance"
    },
    {
      "name": "NIFTY BANK",
      "symbol": "^NSEBANK",
      "value": "54,066.10",
      "change": "-119.85",
      "changePercent": "-0.22",
      "direction": "down",
      "currency": "₹",
      "sourceMode": "yahoo-yfinance"
    },
    {
      "name": "NIFTY IT",
      "symbol": "^CNXIT",
      "value": "29,324.90",
      "change": "-59.55",
      "changePercent": "-0.20",
      "direction": "down",
      "currency": "₹",
      "sourceMode": "yahoo-yfinance"
    },
    {
      "name": "NIFTY AUTO",
      "symbol": "^CNXAUTO",
      "value": "26,198.40",
      "change": "105.60",
      "changePercent": "0.40",
      "direction": "up",
      "currency": "₹",
      "sourceMode": "yahoo-yfinance"
    },
    {
      "name": "NIFTY PHARMA",
      "symbol": "^CNXPHARMA",
      "value": "24,218.10",
      "change": "131.50",
      "changePercent": "0.55",
      "direction": "up",
      "currency": "₹",
      "sourceMode": "yahoo-yfinance"
    }
  ],
  "globalIndices": [
    {
      "name": "S&P 500",
      "symbol": "^GSPC",
      "value": "7,553.68",
      "change": "-56.10",
      "changePercent": "-0.74",
      "direction": "down",
      "sourceMode": "yahoo-yfinance"
    },
    {
      "name": "DOW JONES",
      "symbol": "^DJI",
      "value": "50,687.07",
      "change": "-620.72",
      "changePercent": "-1.21",
      "direction": "down",
      "sourceMode": "yahoo-yfinance"
    },
    {
      "name": "NIKKEI 225",
      "symbol": "^N225",
      "value": "67,470.69",
      "change": "-931.45",
      "changePercent": "-1.36",
      "direction": "down",
      "sourceMode": "yahoo-yfinance"
    },
    {
      "name": "NASDAQ",
      "symbol": "^IXIC",
      "value": "26,853.98",
      "change": "-239.92",
      "changePercent": "-0.89",
      "direction": "down",
      "sourceMode": "yahoo-yfinance"
    },
    {
      "name": "HANG SENG",
      "symbol": "^HSI",
      "value": "25,277.17",
      "change": "-356.04",
      "changePercent": "-1.39",
      "direction": "down",
      "sourceMode": "yahoo-yfinance"
    }
  ],
  "movers": {
    "gainers": [
      {
        "symbol": "ITC",
        "price": "279.75",
        "change": "2.75",
        "changePercent": "0.99",
        "direction": "up",
        "sourceMode": "yahoo-yfinance"
      },
      {
        "symbol": "ICICIBANK",
        "price": "1251.10",
        "change": "9.10",
        "changePercent": "0.73",
        "direction": "up",
        "sourceMode": "yahoo-yfinance"
      },
      {
        "symbol": "WIPRO",
        "price": "204.90",
        "change": "0.80",
        "changePercent": "0.39",
        "direction": "up",
        "sourceMode": "yahoo-yfinance"
      },
      {
        "symbol": "SBIN",
        "price": "974.15",
        "change": "3.70",
        "changePercent": "0.38",
        "direction": "up",
        "sourceMode": "yahoo-yfinance"
      },
      {
        "symbol": "MARUTI",
        "price": "13088.00",
        "change": "44.00",
        "changePercent": "0.34",
        "direction": "up",
        "sourceMode": "yahoo-yfinance"
      }
    ],
    "losers": [
      {
        "symbol": "INFY",
        "price": "1204.10",
        "change": "-18.50",
        "changePercent": "-1.51",
        "direction": "down",
        "sourceMode": "yahoo-yfinance"
      },
      {
        "symbol": "BHARTIARTL",
        "price": "1802.40",
        "change": "-21.70",
        "changePercent": "-1.19",
        "direction": "down",
        "sourceMode": "yahoo-yfinance"
      },
      {
        "symbol": "RELIANCE",
        "price": "1298.10",
        "change": "-15.10",
        "changePercent": "-1.15",
        "direction": "down",
        "sourceMode": "yahoo-yfinance"
      },
      {
        "symbol": "AXISBANK",
        "price": "1248.60",
        "change": "-6.60",
        "changePercent": "-0.53",
        "direction": "down",
        "sourceMode": "yahoo-yfinance"
      },
      {
        "symbol": "SUNPHARMA",
        "price": "1779.30",
        "change": "-9.20",
        "changePercent": "-0.51",
        "direction": "down",
        "sourceMode": "yahoo-yfinance"
      }
    ],
    "source": "yahoo-yfinance"
  },
  "sectorals": [
    {
      "name": "NIFTY BANK",
      "symbol": "^NSEBANK",
      "value": "54,066.10",
      "change": "-119.85",
      "changePercent": "-0.22",
      "direction": "down",
      "currency": "₹",
      "sourceMode": "yahoo-yfinance"
    },
    {
      "name": "NIFTY IT",
      "symbol": "^CNXIT",
      "value": "29,324.90",
      "change": "-59.55",
      "changePercent": "-0.20",
      "direction": "down",
      "currency": "₹",
      "sourceMode": "yahoo-yfinance"
    },
    {
      "name": "NIFTY AUTO",
      "symbol": "^CNXAUTO",
      "value": "26,198.40",
      "change": "105.60",
      "changePercent": "0.40",
      "direction": "up",
      "currency": "₹",
      "sourceMode": "yahoo-yfinance"
    },
    {
      "name": "NIFTY PHARMA",
      "symbol": "^CNXPHARMA",
      "value": "24,218.10",
      "change": "131.50",
      "changePercent": "0.55",
      "direction": "up",
      "currency": "₹",
      "sourceMode": "yahoo-yfinance"
    }
  ],
  "commodities": [
    {
      "name": "Silver",
      "symbol": "SI=F",
      "value": "$73.39",
      "unit": "$/oz",
      "change": "-0.09",
      "changePercent": "-0.12",
      "direction": "down",
      "source": "yahoo-yfinance"
    },
    {
      "name": "Gold",
      "symbol": "GC=F",
      "value": "$4488.40",
      "unit": "$/oz",
      "change": "51.70",
      "changePercent": "1.17",
      "direction": "up",
      "source": "yahoo-yfinance"
    },
    {
      "name": "Crude Oil",
      "symbol": "CL=F",
      "value": "$95.42",
      "unit": "$/bbl",
      "change": "-0.60",
      "changePercent": "-0.62",
      "direction": "down",
      "source": "yahoo-yfinance"
    }
  ],
  "currencies": [
    {
      "name": "USD/INR",
      "pair": "USDINR",
      "symbol": "USDINR=X",
      "value": "₹95.7575",
      "rate": 95.75749969482422,
      "change": "0.4945",
      "changePercent": "0.52",
      "direction": "up",
      "source": "yahoo-yfinance",
      "mode": "fallback-intraday",
      "asOf": "2026-06-04T07:57:26.759670Z"
    },
    {
      "name": "OMR/INR",
      "pair": "OMRINR",
      "symbol": "OMRINR=X",
      "value": "₹248.0500",
      "rate": 248.0500030517578,
      "change": "0.0000",
      "changePercent": "0.00",
      "direction": "up",
      "source": "yahoo-yfinance",
      "mode": "fallback-intraday",
      "asOf": "2026-06-04T07:57:26.776401Z"
    },
    {
      "name": "JPY/INR",
      "pair": "JPYINR",
      "symbol": "JPYINR=X",
      "value": "₹0.5986",
      "rate": 0.5986499786376953,
      "change": "0.0035",
      "changePercent": "0.59",
      "direction": "up",
      "source": "yahoo-yfinance",
      "mode": "fallback-intraday",
      "asOf": "2026-06-04T07:57:26.815606Z"
    },
    {
      "name": "GBP/INR",
      "pair": "GBPINR",
      "symbol": "GBPINR=X",
      "value": "₹128.5200",
      "rate": 128.52000427246094,
      "change": "-0.2925",
      "changePercent": "-0.23",
      "direction": "down",
      "source": "yahoo-yfinance",
      "mode": "fallback-intraday",
      "asOf": "2026-06-04T07:57:26.842921Z"
    },
    {
      "name": "EUR/INR",
      "pair": "EURINR",
      "symbol": "EURINR=X",
      "value": "₹111.1093",
      "rate": 111.10929870605469,
      "change": "0.4723",
      "changePercent": "0.43",
      "direction": "up",
      "source": "yahoo-yfinance",
      "mode": "fallback-intraday",
      "asOf": "2026-06-04T07:57:26.876680Z"
    }
  ],
  "mutualFunds": [
    {
      "instrumentType": "mutualFund",
      "schemeCode": "119550",
      "isinGrowth": "INF209K01YN0",
      "isinDividendReinvestment": "-",
      "name": "Aditya Birla Sun Life Banking & PSU Debt Fund- Direct Plan-Growth",
      "category": "Aditya Birla Sun Life Mutual Fund",
      "nav": 395.5958,
      "navDate": "03-Jun-2026",
      "source": {
        "provider": "amfi_navall",
        "mode": "official-daily",
        "fetchedAt": "2026-06-04T07:57:30.276173Z"
      },
      "extras": {}
    },
    {
      "instrumentType": "mutualFund",
      "schemeCode": "120338",
      "isinGrowth": "INF767K01GI4",
      "isinDividendReinvestment": "-",
      "name": "LIC MF Banking & PSU Fund-Direct Plan-Growth",
      "category": "LIC Mutual Fund",
      "nav": 39.124,
      "navDate": "03-Jun-2026",
      "source": {
        "provider": "amfi_navall",
        "mode": "official-daily",
        "fetchedAt": "2026-06-04T07:57:30.276754Z"
      },
      "extras": {}
    },
    {
      "instrumentType": "mutualFund",
      "schemeCode": "134547",
      "isinGrowth": "INF204KA1U53",
      "isinDividendReinvestment": "-",
      "name": "Nippon India Banking and PSU  Fund- Direct Plan-Growth Plan- Growth Option",
      "category": "Nippon India Mutual Fund",
      "nav": 22.3658,
      "navDate": "03-Jun-2026",
      "source": {
        "provider": "amfi_navall",
        "mode": "official-daily",
        "fetchedAt": "2026-06-04T07:57:30.276816Z"
      },
      "extras": {}
    },
    {
      "instrumentType": "mutualFund",
      "schemeCode": "134552",
      "isinGrowth": "INF204KA1U61",
      "isinDividendReinvestment": "-",
      "name": "Nippon India Banking and PSU Fund- Direct Plan-Growth Plan- Bonus Option",
      "category": "Nippon India Mutual Fund",
      "nav": 22.3652,
      "navDate": "03-Jun-2026",
      "source": {
        "provider": "amfi_navall",
        "mode": "official-daily",
        "fetchedAt": "2026-06-04T07:57:30.276847Z"
      },
      "extras": {}
    },
    {
      "instrumentType": "mutualFund",
      "schemeCode": "149361",
      "isinGrowth": "INF277KA1224",
      "isinDividendReinvestment": "-",
      "name": "Tata Corporate Bond Fund-Direct Plan-Growth",
      "category": "Tata Mutual Fund",
      "nav": 13.1264,
      "navDate": "03-Jun-2026",
      "source": {
        "provider": "amfi_navall",
        "mode": "official-daily",
        "fetchedAt": "2026-06-04T07:57:30.278095Z"
      },
      "extras": {}
    },
    {
      "instrumentType": "mutualFund",
      "schemeCode": "151320",
      "isinGrowth": "INF0GCD01560",
      "isinDividendReinvestment": "-",
      "name": "TRUSTMF CORPORATE BOND FUND-DIRECT PLAN-GROWTH",
      "category": "Trust Mutual Fund",
      "nav": 1249.4653,
      "navDate": "03-Jun-2026",
      "source": {
        "provider": "amfi_navall",
        "mode": "official-daily",
        "fetchedAt": "2026-06-04T07:57:30.278159Z"
      },
      "extras": {}
    },
    {
      "instrumentType": "mutualFund",
      "schemeCode": "140603",
      "isinGrowth": "INF194KA1X61",
      "isinDividendReinvestment": "-",
      "name": "BANDHAN Credit Risk Fund-Direct Plan-Growth",
      "category": "Bandhan Mutual Fund",
      "nav": 18.6046,
      "navDate": "03-Jun-2026",
      "source": {
        "provider": "amfi_navall",
        "mode": "official-daily",
        "fetchedAt": "2026-06-04T07:57:30.278381Z"
      },
      "extras": {}
    },
    {
      "instrumentType": "mutualFund",
      "schemeCode": "118416",
      "isinGrowth": "INF194K01N63",
      "isinDividendReinvestment": "-",
      "name": "BANDHAN Dynamic Bond Fund-Direct Plan-Growth",
      "category": "Bandhan Mutual Fund",
      "nav": 38.9185,
      "navDate": "03-Jun-2026",
      "source": {
        "provider": "amfi_navall",
        "mode": "official-daily",
        "fetchedAt": "2026-06-04T07:57:30.279357Z"
      },
      "extras": {}
    },
    {
      "instrumentType": "mutualFund",
      "schemeCode": "120084",
      "isinGrowth": "INF663L01AD7",
      "isinDividendReinvestment": "-",
      "name": "PGIM India Dynamic Bond Fund - Direct Plan-Growth Option",
      "category": "PGIM India Mutual Fund",
      "nav": 3054.8477,
      "navDate": "03-Jun-2026",
      "source": {
        "provider": "amfi_navall",
        "mode": "official-daily",
        "fetchedAt": "2026-06-04T07:57:30.280015Z"
      },
      "extras": {}
    },
    {
      "instrumentType": "mutualFund",
      "schemeCode": "119097",
      "isinGrowth": "INF277K01MV5",
      "isinDividendReinvestment": "-",
      "name": "Tata Dynamic Bond Fund- Direct Plan-Growth Option",
      "category": "Tata Mutual Fund",
      "nav": 38.2366,
      "navDate": "23-Sep-2022",
      "source": {
        "provider": "amfi_navall",
        "mode": "official-daily",
        "fetchedAt": "2026-06-04T07:57:30.280093Z"
      },
      "extras": {}
    },
    {
      "instrumentType": "mutualFund",
      "schemeCode": "122646",
      "isinGrowth": "INF209K01UX7",
      "isinDividendReinvestment": "-",
      "name": "Aditya Birla Sun Life Floating Rate Fund-Direct Plan-Growth",
      "category": "Aditya Birla Sun Life Mutual Fund",
      "nav": 376.8756,
      "navDate": "03-Jun-2026",
      "source": {
        "provider": "amfi_navall",
        "mode": "official-daily",
        "fetchedAt": "2026-06-04T07:57:30.280229Z"
      },
      "extras": {}
    },
    {
      "instrumentType": "mutualFund",
      "schemeCode": "147269",
      "isinGrowth": "INF174KA1EC0",
      "isinDividendReinvestment": "-",
      "name": "KOTAK FLOATING RATE FUND-DIRECT PLAN-GROWTH OPTION",
      "category": "Kotak Mahindra Mutual Fund",
      "nav": 1627.7214,
      "navDate": "03-Jun-2026",
      "source": {
        "provider": "amfi_navall",
        "mode": "official-daily",
        "fetchedAt": "2026-06-04T07:57:30.280596Z"
      },
      "extras": {}
    },
    {
      "instrumentType": "mutualFund",
      "schemeCode": "149007",
      "isinGrowth": "INF277KA1026",
      "isinDividendReinvestment": "-",
      "name": "Tata Floating Rate Fund -Direct Plan-Growth",
      "category": "Tata Mutual Fund",
      "nav": 13.6581,
      "navDate": "03-Jun-2026",
      "source": {
        "provider": "amfi_navall",
        "mode": "official-daily",
        "fetchedAt": "2026-06-04T07:57:30.280695Z"
      },
      "extras": {}
    },
    {
      "instrumentType": "mutualFund",
      "schemeCode": "120282",
      "isinGrowth": "INF767K01EZ3",
      "isinDividendReinvestment": "-",
      "name": "LIC MF Gilt Fund-Direct Plan-Growth",
      "category": "LIC Mutual Fund",
      "nav": 64.9008,
      "navDate": "03-Jun-2026",
      "source": {
        "provider": "amfi_navall",
        "mode": "official-daily",
        "fetchedAt": "2026-06-04T07:57:30.281257Z"
      },
      "extras": {}
    },
    {
      "instrumentType": "mutualFund",
      "schemeCode": "125349",
      "isinGrowth": "-",
      "isinDividendReinvestment": "INF579M01688",
      "name": "360 ONE LIQUID FUND DIRECT PLAN  DAILY DIVIDEND REINVESTMENT",
      "category": "360 ONE Mutual Fund",
      "nav": 1000.1661,
      "navDate": "03-Jun-2026",
      "source": {
        "provider": "amfi_navall",
        "mode": "official-daily",
        "fetchedAt": "2026-06-04T07:57:30.281722Z"
      },
      "extras": {}
    },
    {
      "instrumentType": "mutualFund",
      "schemeCode": "125345",
      "isinGrowth": "INF579M01621",
      "isinDividendReinvestment": "-",
      "name": "360 ONE LIQUID FUND DIRECT PLAN  GROWTH",
      "category": "360 ONE Mutual Fund",
      "nav": 2135.6901,
      "navDate": "03-Jun-2026",
      "source": {
        "provider": "amfi_navall",
        "mode": "official-daily",
        "fetchedAt": "2026-06-04T07:57:30.281726Z"
      },
      "extras": {}
    },
    {
      "instrumentType": "mutualFund",
      "schemeCode": "125343",
      "isinGrowth": "INF579M01639",
      "isinDividendReinvestment": "INF579M01696",
      "name": "360 ONE LIQUID FUND DIRECT PLAN  WEEKLY DIVIDEND",
      "category": "360 ONE Mutual Fund",
      "nav": 1005.1495,
      "navDate": "03-Jun-2026",
      "source": {
        "provider": "amfi_navall",
        "mode": "official-daily",
        "fetchedAt": "2026-06-04T07:57:30.281730Z"
      },
      "extras": {}
    },
    {
      "instrumentType": "mutualFund",
      "schemeCode": "125342",
      "isinGrowth": "-",
      "isinDividendReinvestment": "INF579M01563",
      "name": "360 ONE LIQUID FUND REGULAR PLAN  DAILY DIVIDEND REINVESTMENT",
      "category": "360 ONE Mutual Fund",
      "nav": 1000.1661,
      "navDate": "03-Jun-2026",
      "source": {
        "provider": "amfi_navall",
        "mode": "official-daily",
        "fetchedAt": "2026-06-04T07:57:30.281736Z"
      },
      "extras": {}
    },
    {
      "instrumentType": "mutualFund",
      "schemeCode": "125259",
      "isinGrowth": "INF579M01506",
      "isinDividendReinvestment": "-",
      "name": "360 ONE LIQUID FUND REGULAR PLAN  GROWTH",
      "category": "360 ONE Mutual Fund",
      "nav": 2120.4571,
      "navDate": "03-Jun-2026",
      "source": {
        "provider": "amfi_navall",
        "mode": "official-daily",
        "fetchedAt": "2026-06-04T07:57:30.281739Z"
      },
      "extras": {}
    },
    {
      "instrumentType": "mutualFund",
      "schemeCode": "125337",
      "isinGrowth": "INF579M01514",
      "isinDividendReinvestment": "INF579M01571",
      "name": "360 ONE LIQUID FUND REGULAR PLAN  WEEKLY DIVIDEND",
      "category": "360 ONE Mutual Fund",
      "nav": 1005.1343,
      "navDate": "03-Jun-2026",
      "source": {
        "provider": "amfi_navall",
        "mode": "official-daily",
        "fetchedAt": "2026-06-04T07:57:30.281743Z"
      },
      "extras": {}
    },
    {
      "instrumentType": "mutualFund",
      "schemeCode": "154049",
      "isinGrowth": "-",
      "isinDividendReinvestment": "INF2JJD01011",
      "name": "Abakkus Liquid Fund - Direct Plan - Daily IDCW Reinvestment",
      "category": "Abakkus Mutual Fund",
      "nav": 100.0527,
      "navDate": "03-Jun-2026",
      "source": {
        "provider": "amfi_navall",
        "mode": "official-daily",
        "fetchedAt": "2026-06-04T07:57:30.281748Z"
      },
      "extras": {}
    },
    {
      "instrumentType": "mutualFund",
      "schemeCode": "154051",
      "isinGrowth": "INF2JJD01029",
      "isinDividendReinvestment": "-",
      "name": "Abakkus Liquid Fund - Direct Plan - Growth",
      "category": "Abakkus Mutual Fund",
      "nav": 102.6512,
      "navDate": "03-Jun-2026",
      "source": {
        "provider": "amfi_navall",
        "mode": "official-daily",
        "fetchedAt": "2026-06-04T07:57:30.281752Z"
      },
      "extras": {}
    },
    {
      "instrumentType": "mutualFund",
      "schemeCode": "154055",
      "isinGrowth": "-",
      "isinDividendReinvestment": "INF2JJD01037",
      "name": "Abakkus Liquid Fund - Direct Plan - Monthly IDCW Reinvestment",
      "category": "Abakkus Mutual Fund",
      "nav": 100.3463,
      "navDate": "03-Jun-2026",
      "source": {
        "provider": "amfi_navall",
        "mode": "official-daily",
        "fetchedAt": "2026-06-04T07:57:30.281757Z"
      },
      "extras": {}
    },
    {
      "instrumentType": "mutualFund",
      "schemeCode": "154052",
      "isinGrowth": "-",
      "isinDividendReinvestment": "INF2JJD01052",
      "name": "Abakkus Liquid Fund - Direct Plan - Quarterly IDCW Reinvestment",
      "category": "Abakkus Mutual Fund",
      "nav": 100.9577,
      "navDate": "03-Jun-2026",
      "source": {
        "provider": "amfi_navall",
        "mode": "official-daily",
        "fetchedAt": "2026-06-04T07:57:30.281763Z"
      },
      "extras": {}
    },
    {
      "instrumentType": "mutualFund",
      "schemeCode": "154050",
      "isinGrowth": "-",
      "isinDividendReinvestment": "INF2JJD01045",
      "name": "Abakkus Liquid Fund - Direct Plan - Weekly IDCW Reinvestment",
      "category": "Abakkus Mutual Fund",
      "nav": 100.0847,
      "navDate": "03-Jun-2026",
      "source": {
        "provider": "amfi_navall",
        "mode": "official-daily",
        "fetchedAt": "2026-06-04T07:57:30.281767Z"
      },
      "extras": {}
    },
    {
      "instrumentType": "mutualFund",
      "schemeCode": "154053",
      "isinGrowth": "-",
      "isinDividendReinvestment": "INF2JJD01060",
      "name": "Abakkus Liquid Fund - Regular Plan - Daily IDCW Reinvestment",
      "category": "Abakkus Mutual Fund",
      "nav": 100.0527,
      "navDate": "03-Jun-2026",
      "source": {
        "provider": "amfi_navall",
        "mode": "official-daily",
        "fetchedAt": "2026-06-04T07:57:30.281772Z"
      },
      "extras": {}
    },
    {
      "instrumentType": "mutualFund",
      "schemeCode": "154047",
      "isinGrowth": "INF2JJD01078",
      "isinDividendReinvestment": "-",
      "name": "Abakkus Liquid Fund - Regular Plan - Growth",
      "category": "Abakkus Mutual Fund",
      "nav": 102.6116,
      "navDate": "03-Jun-2026",
      "source": {
        "provider": "amfi_navall",
        "mode": "official-daily",
        "fetchedAt": "2026-06-04T07:57:30.281776Z"
      },
      "extras": {}
    },
    {
      "instrumentType": "mutualFund",
      "schemeCode": "154048",
      "isinGrowth": "-",
      "isinDividendReinvestment": "INF2JJD01086",
      "name": "Abakkus Liquid Fund - Regular Plan - Monthly IDCW Reinvestment",
      "category": "Abakkus Mutual Fund",
      "nav": 100.3424,
      "navDate": "03-Jun-2026",
      "source": {
        "provider": "amfi_navall",
        "mode": "official-daily",
        "fetchedAt": "2026-06-04T07:57:30.281782Z"
      },
      "extras": {}
    },
    {
      "instrumentType": "mutualFund",
      "schemeCode": "154054",
      "isinGrowth": "-",
      "isinDividendReinvestment": "INF2JJD01102",
      "name": "Abakkus Liquid Fund - Regular Plan - Quarterly IDCW Reinvestment",
      "category": "Abakkus Mutual Fund",
      "nav": 100.9198,
      "navDate": "03-Jun-2026",
      "source": {
        "provider": "amfi_navall",
        "mode": "official-daily",
        "fetchedAt": "2026-06-04T07:57:30.281786Z"
      },
      "extras": {}
    },
    {
      "instrumentType": "mutualFund",
      "schemeCode": "154056",
      "isinGrowth": "-",
      "isinDividendReinvestment": "INF2JJD01094",
      "name": "Abakkus Liquid Fund - Regular Plan - Weekly IDCW Reinvestment",
      "category": "Abakkus Mutual Fund",
      "nav": 100.0809,
      "navDate": "03-Jun-2026",
      "source": {
        "provider": "amfi_navall",
        "mode": "official-daily",
        "fetchedAt": "2026-06-04T07:57:30.281790Z"
      },
      "extras": {}
    },
    {
      "instrumentType": "mutualFund",
      "schemeCode": "100047",
      "isinGrowth": "INF209K01RU9",
      "isinDividendReinvestment": "-",
      "name": "Aditya Birla Sun Life Liquid Fund - Growth",
      "category": "Aditya Birla Sun Life Mutual Fund",
      "nav": 444.5941,
      "navDate": "03-Jun-2026",
      "source": {
        "provider": "amfi_navall",
        "mode": "official-daily",
        "fetchedAt": "2026-06-04T07:57:30.281796Z"
      },
      "extras": {}
    },
    {
      "instrumentType": "mutualFund",
      "schemeCode": "119568",
      "isinGrowth": "INF209K01VA3",
      "isinDividendReinvestment": "-",
      "name": "Aditya Birla Sun Life Liquid Fund - Growth - Direct Plan",
      "category": "Aditya Birla Sun Life Mutual Fund",
      "nav": 450.5148,
      "navDate": "03-Jun-2026",
      "source": {
        "provider": "amfi_navall",
        "mode": "official-daily",
        "fetchedAt": "2026-06-04T07:57:30.281800Z"
      },
      "extras": {}
    },
    {
      "instrumentType": "mutualFund",
      "schemeCode": "100046",
      "isinGrowth": "INF209K01KQ2",
      "isinDividendReinvestment": "INF209K01SQ5",
      "name": "Aditya Birla Sun Life Liquid Fund -Daily IDCW",
      "category": "Aditya Birla Sun Life Mutual Fund",
      "nav": 100.195,
      "navDate": "03-Jun-2026",
      "source": {
        "provider": "amfi_navall",
        "mode": "official-daily",
        "fetchedAt": "2026-06-04T07:57:30.281804Z"
      },
      "extras": {}
    },
    {
      "instrumentType": "mutualFund",
      "schemeCode": "119569",
      "isinGrowth": "INF209K01UZ2",
      "isinDividendReinvestment": "-",
      "name": "Aditya Birla Sun Life Liquid Fund -Direct - daily IDCW",
      "category": "Aditya Birla Sun Life Mutual Fund",
      "nav": 100.195,
      "navDate": "03-Jun-2026",
      "source": {
        "provider": "amfi_navall",
        "mode": "official-daily",
        "fetchedAt": "2026-06-04T07:57:30.281808Z"
      },
      "extras": {}
    },
    {
      "instrumentType": "mutualFund",
      "schemeCode": "119571",
      "isinGrowth": "INF209K01VD7",
      "isinDividendReinvestment": "-",
      "name": "Aditya Birla Sun Life Liquid Fund -DIRECT - IDCW",
      "category": "Aditya Birla Sun Life Mutual Fund",
      "nav": 144.1379,
      "navDate": "03-Jun-2026",
      "source": {
        "provider": "amfi_navall",
        "mode": "official-daily",
        "fetchedAt": "2026-06-04T07:57:30.281812Z"
      },
      "extras": {}
    },
    {
      "instrumentType": "mutualFund",
      "schemeCode": "119570",
      "isinGrowth": "INF209K01VC9",
      "isinDividendReinvestment": "-",
      "name": "Aditya Birla Sun Life Liquid Fund -Direct - weekly IDCW",
      "category": "Aditya Birla Sun Life Mutual Fund",
      "nav": 100.3149,
      "navDate": "03-Jun-2026",
      "source": {
        "provider": "amfi_navall",
        "mode": "official-daily",
        "fetchedAt": "2026-06-04T07:57:30.281816Z"
      },
      "extras": {}
    },
    {
      "instrumentType": "mutualFund",
      "schemeCode": "100041",
      "isinGrowth": "-",
      "isinDividendReinvestment": "INF209K01KN9",
      "name": "Aditya Birla Sun Life Liquid Fund -Institutional - IDCW",
      "category": "Aditya Birla Sun Life Mutual Fund",
      "nav": 108.023,
      "navDate": "03-Jun-2026",
      "source": {
        "provider": "amfi_navall",
        "mode": "official-daily",
        "fetchedAt": "2026-06-04T07:57:30.281821Z"
      },
      "extras": {}
    },
    {
      "instrumentType": "mutualFund",
      "schemeCode": "100048",
      "isinGrowth": "INF209KA1LK7",
      "isinDividendReinvestment": "INF209K01KY6",
      "name": "Aditya Birla Sun Life Liquid Fund -Institutional - weekly  IDCW",
      "category": "Aditya Birla Sun Life Mutual Fund",
      "nav": 108.2863,
      "navDate": "03-Jun-2026",
      "source": {
        "provider": "amfi_navall",
        "mode": "official-daily",
        "fetchedAt": "2026-06-04T07:57:30.281826Z"
      },
      "extras": {}
    },
    {
      "instrumentType": "mutualFund",
      "schemeCode": "103885",
      "isinGrowth": "INF209KA1LI1",
      "isinDividendReinvestment": "-",
      "name": "Aditya Birla Sun Life Liquid Fund -Regular - IDCW",
      "category": "Aditya Birla Sun Life Mutual Fund",
      "nav": 109.6442,
      "navDate": "03-Jun-2026",
      "source": {
        "provider": "amfi_navall",
        "mode": "official-daily",
        "fetchedAt": "2026-06-04T07:57:30.281830Z"
      },
      "extras": {}
    },
    {
      "instrumentType": "mutualFund",
      "schemeCode": "100044",
      "isinGrowth": "-",
      "isinDividendReinvestment": "INF209K01KP4",
      "name": "Aditya Birla Sun Life Liquid Fund -Retail - IDCW",
      "category": "Aditya Birla Sun Life Mutual Fund",
      "nav": 163.694,
      "navDate": "03-Jun-2026",
      "source": {
        "provider": "amfi_navall",
        "mode": "official-daily",
        "fetchedAt": "2026-06-04T07:57:30.281834Z"
      },
      "extras": {}
    },
    {
      "instrumentType": "mutualFund",
      "schemeCode": "100051",
      "isinGrowth": "INF209K01KU4",
      "isinDividendReinvestment": "INF209KA1LJ9",
      "name": "Aditya Birla Sun Life Liquid Fund -weekly IDCW",
      "category": "Aditya Birla Sun Life Mutual Fund",
      "nav": 100.3128,
      "navDate": "03-Jun-2026",
      "source": {
        "provider": "amfi_navall",
        "mode": "official-daily",
        "fetchedAt": "2026-06-04T07:57:30.281838Z"
      },
      "extras": {}
    },
    {
      "instrumentType": "mutualFund",
      "schemeCode": "112014",
      "isinGrowth": "INF209K01KZ3",
      "isinDividendReinvestment": "-",
      "name": "Aditya Birla Sun Life Liquid Fund- Discipline Advantage Plan",
      "category": "Aditya Birla Sun Life Mutual Fund",
      "nav": 301.5027,
      "navDate": "03-Jun-2026",
      "source": {
        "provider": "amfi_navall",
        "mode": "official-daily",
        "fetchedAt": "2026-06-04T07:57:30.281842Z"
      },
      "extras": {}
    },
    {
      "instrumentType": "mutualFund",
      "schemeCode": "100043",
      "isinGrowth": "INF209K01RT1",
      "isinDividendReinvestment": "-",
      "name": "Aditya Birla Sun Life Liquid Fund-Institutional (Growth)",
      "category": "Aditya Birla Sun Life Mutual Fund",
      "nav": 740.392,
      "navDate": "03-Jun-2026",
      "source": {
        "provider": "amfi_navall",
        "mode": "official-daily",
        "fetchedAt": "2026-06-04T07:57:30.281846Z"
      },
      "extras": {}
    },
    {
      "instrumentType": "mutualFund",
      "schemeCode": "100042",
      "isinGrowth": "INF209K01ME4",
      "isinDividendReinvestment": "-",
      "name": "Aditya Birla Sun Life Liquid Fund-Retail (Growth)",
      "category": "Aditya Birla Sun Life Mutual Fund",
      "nav": 721.4841,
      "navDate": "03-Jun-2026",
      "source": {
        "provider": "amfi_navall",
        "mode": "official-daily",
        "fetchedAt": "2026-06-04T07:57:30.281850Z"
      },
      "extras": {}
    },
    {
      "instrumentType": "mutualFund",
      "schemeCode": "128954",
      "isinGrowth": "INF846K01NH4",
      "isinDividendReinvestment": "-",
      "name": "Axis Liquid Fund - Direct plan - Bonus Option",
      "category": "Axis Mutual Fund",
      "nav": 2215.5705,
      "navDate": "05-May-2020",
      "source": {
        "provider": "amfi_navall",
        "mode": "official-daily",
        "fetchedAt": "2026-06-04T07:57:30.281856Z"
      },
      "extras": {}
    },
    {
      "instrumentType": "mutualFund",
      "schemeCode": "120388",
      "isinGrowth": "-",
      "isinDividendReinvestment": "INF846K01DA0",
      "name": "Axis Liquid Fund - Direct Plan - Daily IDCW",
      "category": "Axis Mutual Fund",
      "nav": 1000.956,
      "navDate": "03-Jun-2026",
      "source": {
        "provider": "amfi_navall",
        "mode": "official-daily",
        "fetchedAt": "2026-06-04T07:57:30.281860Z"
      },
      "extras": {}
    },
    {
      "instrumentType": "mutualFund",
      "schemeCode": "120389",
      "isinGrowth": "INF846K01CX4",
      "isinDividendReinvestment": "-",
      "name": "Axis Liquid Fund - Direct Plan - Growth Option",
      "category": "Axis Mutual Fund",
      "nav": 3102.4662,
      "navDate": "03-Jun-2026",
      "source": {
        "provider": "amfi_navall",
        "mode": "official-daily",
        "fetchedAt": "2026-06-04T07:57:30.281864Z"
      },
      "extras": {}
    },
    {
      "instrumentType": "mutualFund",
      "schemeCode": "120391",
      "isinGrowth": "INF846K01CY2",
      "isinDividendReinvestment": "INF846K01CZ9",
      "name": "Axis Liquid Fund - Direct Plan - Monthly IDCW",
      "category": "Axis Mutual Fund",
      "nav": 1002.3589,
      "navDate": "03-Jun-2026",
      "source": {
        "provider": "amfi_navall",
        "mode": "official-daily",
        "fetchedAt": "2026-06-04T07:57:30.281868Z"
      },
      "extras": {}
    },
    {
      "instrumentType": "mutualFund",
      "schemeCode": "120390",
      "isinGrowth": "INF846K01DB8",
      "isinDividendReinvestment": "INF846K01DC6",
      "name": "Axis Liquid Fund - Direct Plan - Weekly IDCW",
      "category": "Axis Mutual Fund",
      "nav": 1002.3809,
      "navDate": "03-Jun-2026",
      "source": {
        "provider": "amfi_navall",
        "mode": "official-daily",
        "fetchedAt": "2026-06-04T07:57:30.281873Z"
      },
      "extras": {}
    },
    {
      "instrumentType": "mutualFund",
      "schemeCode": "112211",
      "isinGrowth": "-",
      "isinDividendReinvestment": "INF846K01420",
      "name": "Axis Liquid Fund - Regular Plan - Daily IDCW",
      "category": "Axis Mutual Fund",
      "nav": 1001.3998,
      "navDate": "03-Jun-2026",
      "source": {
        "provider": "amfi_navall",
        "mode": "official-daily",
        "fetchedAt": "2026-06-04T07:57:30.281877Z"
      },
      "extras": {}
    }
  ],
  "ipo": {
    "upcoming": [],
    "live": [],
    "recent": []
  },
  "nfo": [],
  "stockCategories": {
    "highs": [],
    "lows": [],
    "all": []
  },
  "fiidii": {
    "fii": {},
    "dii": {},
    "date": ""
  },
  "sourceHealth": {
    "indices": {
      "status": "ok",
      "provider": "yahoo_yfinance",
      "mode": "ok",
      "message": "6 Indian indices fetched"
    },
    "globalIndices": {
      "status": "ok",
      "provider": "yahoo_yfinance",
      "mode": "ok",
      "message": "5 global indices fetched"
    },
    "movers": {
      "status": "ok",
      "provider": "yahoo_yfinance",
      "mode": "ok",
      "message": "16 stocks scanned for movers"
    },
    "commodities": {
      "status": "ok",
      "provider": "yahoo_yfinance",
      "mode": "ok",
      "message": "3 commodity rows fetched"
    },
    "fx": {
      "status": "ok",
      "provider": "yahoo_yfinance",
      "mode": "ok",
      "message": "RBI reference scrape failed: 418 Client Error: Unknown Code for url: https://www.rbi.org.in/scripts/ReferenceRateArchive.aspx; 5 FX pairs fetched from Yahoo fallback"
    },
    "mutualFunds": {
      "status": "ok",
      "provider": "amfi_navall",
      "mode": "ok",
      "message": "14211 AMFI NAV rows parsed; 300 selected"
    },
    "eodBhavcopy": {
      "status": "failed",
      "provider": "none",
      "mode": "failed",
      "message": "nse_bhavcopy bhavcopy unavailable from known candidate URLs; bse_bhavcopy bhavcopy unavailable from known candidate URLs"
    }
  },
  "errors": {}
}
