{
  "chennai": {
    "name": "Chennai",
    "sourceMode": "snapshot",
    "fetchedAt": 1744348800000,
    "current": {
      "temp": 34,
      "feelsLike": 39,
      "condition": "Partly Cloudy",
      "icon": "⛅"
    },
    "morning": { "temp": 31, "rainMm": "-", "humidity": 70 },
    "noon": { "temp": 35, "rainMm": "-", "humidity": 58 },
    "evening": { "temp": 32, "rainMm": "1.2mm", "humidity": 73 }
  },
  "trichy": {
    "name": "Trichy",
    "sourceMode": "snapshot",
    "fetchedAt": 1744348800000,
    "current": {
      "temp": 38,
      "feelsLike": 42,
      "condition": "Sunny",
      "icon": "☀️"
    },
    "morning": { "temp": 33, "rainMm": "-", "humidity": 60 },
    "noon": { "temp": 38, "rainMm": "-", "humidity": 45 },
    "evening": { "temp": 35, "rainMm": "-", "humidity": 50 }
  },
  "muscat": {
    "name": "Muscat",
    "sourceMode": "snapshot",
    "fetchedAt": 1744348800000,
    "current": {
      "temp": 28,
      "feelsLike": 30,
      "condition": "Clear",
      "icon": "🌙"
    },
    "morning": { "temp": 26, "rainMm": "-", "humidity": 50 },
    "noon": { "temp": 30, "rainMm": "-", "humidity": 40 },
    "evening": { "temp": 27, "rainMm": "-", "humidity": 55 }
  }
}
